verify_oidc_token/__init__.py
verify_oidc_token/__main__.py
verify_oidc_token/cli.py
verify_oidc_token-0.1.0.dist-info/METADATA
verify_oidc_token-0.1.0.dist-info/WHEEL
verify_oidc_token-0.1.0.dist-info/entry_points.txt
verify_oidc_token-0.1.0.dist-info/licenses/LICENSE
verify_oidc_token-0.1.0.dist-info/RECORD
