Metadata-Version: 2.3
Name: verify-oidc-token
Version: 0.1.0
Summary: A tool to verify OIDC tokens
Project-URL: GitHub, https://github.com/ei-grad/verify-oidc-token
Author-email: Andrew Grigorev <andrew@ei-grad.ru>
License-Expression: MIT
License-File: LICENSE
Classifier: Development Status :: 4 - Beta
Classifier: Environment :: Console
Classifier: Intended Audience :: Developers
Classifier: Intended Audience :: System Administrators
Classifier: Programming Language :: Python :: 3
Classifier: Topic :: Security
Classifier: Topic :: Security :: Cryptography
Requires-Python: >=3.8
Requires-Dist: cryptography
Requires-Dist: pyjwt<3.0.0,>=2.0.0
Requires-Dist: requests<3.0.0,>=2.25.0
